{"cv":16,"name":"persvector","fqn":"nim-persistent-vector.PMunch.github.com","head":"3f92a26aced63c4d443f62a31402329a1c18d22e","author":"Peter Munch-Ellingsen","description":"Implementation of Clojures persistent vector in Nim for easy immutable lists.","license":"MIT","nim":"0.17.1","skipFiles":["example.nim"],"releases":[{"v":"1.0.0@b691dfa0533c4de6b2dcac208efa87ec59c61b89","r":[]},{"v":"#head@3f92a26aced63c4d443f62a31402329a1c18d22e","r":[]}],"generatedAt":"2026-05-23T21:32:42Z","allDeps":{"packages":[],"urls":[],"unresolved":[]}}