{
  "cv": 19,
  "name": "bson",
  "fqn": "bson.JohnAD.github.com",
  "current": "38babfaaf8ebffefd223d63c313bcbf2f3a992c3",
  "author": "John Dupuy",
  "description": "BSON (Binary Json) serialization",
  "license": "MIT",
  "nim": "1.0.0",
  "srcDir": "src",
  "releases": [
    {
      "v": "1.1.2@9d54157ee9f4a2860582c79f579a9ba7d15f9f59",
      "r": []
    },
    {
      "v": "1.1.1@d3aa6b50adeed2b73c59d39161e31af67a42cb80",
      "r": []
    },
    {
      "v": "1.0.1@8d801326e8f7fb056ecd36bc0863000558cfcad1",
      "r": []
    },
    {
      "v": "1.0.0@ca350238341f1a05e6a63d9516d9cc88919b1c48",
      "r": []
    }
  ],
  "releaseCacheVersion": 19,
  "tags": true,
  "generatedAt": "2026-05-28T00:44:14Z",
  "forge": {
    "archives": {
      "tar.gz": "/archive/refs/tags/{tag}.tar.gz",
      "zip": "/archive/refs/tags/{tag}.zip"
    },
    "releases": [
      "v1.0.0",
      "v1.0.1",
      "v1.1.1",
      "v1.1.2"
    ],
    "tagVersions": {
      "v1.0.0": "1.0.0",
      "v1.0.1": "1.0.1",
      "v1.1.1": "1.1.1",
      "v1.1.2": "1.1.2"
    },
    "latest": "v1.1.2"
  },
  "allDeps": {
    "packages": [],
    "urls": [],
    "unresolved": []
  }
}