{
  "cv": 17,
  "name": "palladian",
  "fqn": "nim-palladian.itsumura-h.github.com",
  "head": "6d953b7bf1c340d55d944418f78151dc931f987f",
  "releases": [
    {
      "v": "0.2.0@6d953b7bf1c340d55d944418f78151dc931f987f^",
      "r": [],
      "S": "HasUnknownNimbleFile",
      "E": "ambiguous nimble file"
    },
    {
      "v": "#head@6d953b7bf1c340d55d944418f78151dc931f987f",
      "r": [],
      "S": "HasUnknownNimbleFile",
      "E": "ambiguous nimble file"
    }
  ],
  "tags": true,
  "generatedAt": "2026-05-25T11:50:13Z",
  "forge": {
    "archives": {
      "tar.gz": "/archive/refs/tags/{tag}.tar.gz",
      "zip": "/archive/refs/tags/{tag}.zip"
    },
    "releases": [
      "v0.2.0"
    ],
    "tagVersions": {
      "v0.2.0": "0.2.0"
    },
    "latest": "v0.2.0"
  },
  "allDeps": {
    "packages": [],
    "urls": [],
    "unresolved": []
  }
}