{
  "cv": 17,
  "name": "nimcb",
  "fqn": "nimcb.AdrianV.github.com",
  "head": "b07815e1f0174da6035e9570f390dd9b833b715a",
  "author": "Adrian Veith",
  "description": "Integrate nim projects in the C++Builder build process",
  "license": "MIT",
  "nim": "0.18.1",
  "srcDir": "src",
  "bin": [
    "nimcb"
  ],
  "releases": [
    {
      "v": "0.1.0@13ed89d5259a9b6ef32777650dba5bd63e206112",
      "r": [],
      "m": "~",
      "s": "",
      "p": []
    },
    {
      "v": "#head@b07815e1f0174da6035e9570f390dd9b833b715a",
      "r": [],
      "m": "~",
      "s": "",
      "p": []
    }
  ],
  "tags": true,
  "generatedAt": "2026-05-26T00:51:34Z",
  "allDeps": {
    "packages": [],
    "urls": [],
    "unresolved": []
  }
}