{"cv":17,"name":"awsSTS","fqn":"nim_awsSTS.ThomasTJdev.github.com","head":"4170b92e4b6be92319c8c09717b61073fcde02d7","author":"Thomas T. Jarløv (https://github.com/ThomasTJdev)","description":"AWS Security Token Service API in Nim","license":"MIT","nim":"1.6.18","srcDir":"src","releases":[{"v":"2.1.0@4170b92e4b6be92319c8c09717b61073fcde02d7^","r":["awsSigV4 >= 0.0.2"]},{"v":"2.0.3@a61046658293b25bdd7ecb050fed46058333a2f8","r":["awsSigV4 >= 0.0.2"]},{"v":"2.0.2@7546de050fead13448232b2dec663ee1739fcdc1","r":["awsSigV4 >= 0.0.2"]},{"v":"2.0.1@20baf1f4a060885ce9d980323bb92a9ac58be113","r":["awsSigV4 >= 0.0.2"]},{"v":"2.0.0@8238139344ddae36dc79a8360dd66bdf97ff341c","r":["awsSigV4 0.0.1"]},{"v":"1.0.3@5bf72edf498b038b11a6e24e031b867806ccf427","r":["sigv4 1.3.0"],"m":"1.4.2","s":""},{"v":"1.0.2@9577ef2dacb801a66ce347d5ec5f87e8cfe7423c","r":["sigv4 1.2.1"],"m":"1.4.2","s":""},{"v":"1.0.1@2c8ea35ea649bda4aef1bbfa597fc1c7bfb9f7fa","r":["sigv4 1.2.1"],"m":"1.4.2","s":""},{"v":"1.0.0@e74dcea40e797bdda708f795c0e37ba71b06cc67","r":["sigv4 1.2.1"],"m":"1.4.2","s":""},{"v":"#head@4170b92e4b6be92319c8c09717b61073fcde02d7","r":["awsSigV4 >= 0.0.2"]}],"tags":true,"generatedAt":"2026-05-24T16:34:28Z","allDeps":{"packages":["awsSigV4 > 1.0.3","crunchy > 1.0.3","nimSHA2 <= 1.0.3","nimcrypto <= 1.0.3","nimsimd > 1.0.3","sigv4 <= 1.0.3"],"urls":[],"unresolved":["gh:disruptek/nimcrypto","gh:ThomasTJdev/crunchy"]},"forge":{"archives":{"tar.gz":"/archive/refs/tags/{tag}.tar.gz","zip":"/archive/refs/tags/{tag}.zip"},"releases":["v2.0.0"],"tagVersions":{"v2.0.0":"2.0.0"},"latest":"v2.0.0"}}