{
  "cv": 19,
  "name": "WebGL",
  "fqn": "webgl.stisa.github.com",
  "current": "1196ef8df277dd70cab70972c738108a8e0e8481",
  "author": "stisa",
  "description": "Basic wrapper for WebGL.",
  "license": "MIT",
  "nim": "0.16.1",
  "srcDir": "src",
  "skipDirs": [
    "oldwrapper",
    "templates"
  ],
  "releases": [
    {
      "v": "0.2.1@18ef9a0ce37824779e6cf2c2c6a9ba72b4c120f5",
      "r": []
    },
    {
      "v": "0.2.0@9103431db30d1d29e2225255351001d5f8635506",
      "r": []
    },
    {
      "v": "0.1.2@76809269a62bf6be3784550d1f98166afa856516",
      "r": [],
      "m": "0.16.0"
    },
    {
      "v": "0.1.0@e1f2f2563749307680dd6d960129022d03471f4e",
      "r": [],
      "m": "0.14.0",
      "x": []
    }
  ],
  "releaseCacheVersion": 19,
  "tags": true,
  "generatedAt": "2026-05-28T13:23:33Z",
  "forge": {
    "archives": {
      "tar.gz": "/archive/refs/tags/{tag}.tar.gz",
      "zip": "/archive/refs/tags/{tag}.zip"
    },
    "releases": [
      "0.2.1"
    ],
    "prerelease": [
      "0.2.1"
    ]
  },
  "allDeps": {
    "packages": [],
    "urls": [],
    "unresolved": []
  }
}