{
  "cv": 17,
  "name": "baker",
  "fqn": "baker.jasonrbriggs.github.com",
  "head": "1d45935b6da43fb60f5f6511edfb04090cc9e6b3",
  "author": "Jason R Briggs",
  "description": "Static website generation",
  "license": "Apache-2.0",
  "nim": "1.0.0",
  "srcDir": "src",
  "bin": [
    "baker"
  ],
  "releases": [
    {
      "v": "2.0.9@7ec80e4ca4b19239c4ae6864bd5683d0e25f0857",
      "r": [
        "proton >= 0.2.4",
        "docopt >= 0.6.8",
        "markdown #v0.8.1",
        "zip >= 0.2.1",
        "timezones >= 0.5.3",
        "ndb >= 0.19.4"
      ]
    },
    {
      "v": "2.0.7@4c4f11763bd97802206ce793da9519f54f00f0ce",
      "r": [
        "proton >= 0.2.4",
        "docopt #head",
        "markdown >= 0.2.0",
        "zip >= 0.2.1",
        "timezones >= 0.5.0",
        "ndb >= 0.19.4"
      ]
    },
    {
      "v": "2.0.5@6fe28400d0b6b658a8429d0beead0780a44c06a0",
      "r": [
        "proton >= 0.2.4",
        "docopt #head",
        "markdown >= 0.2.0",
        "zip >= 0.2.1",
        "timezones >= 0.5.0",
        "ndb >= 0.19.4"
      ],
      "m": "0.20.0"
    },
    {
      "v": "2.0.4@d6d153813fe6cd4e312f911723ee95bb9e388de8",
      "r": [
        "proton >= 0.2.4",
        "docopt #head",
        "markdown >= 0.2.0",
        "zip >= 0.2.1",
        "timezones >= 0.5.0",
        "ndb >= 0.19.4"
      ],
      "m": "0.20.0"
    },
    {
      "v": "2.0.3@c0ca825e47317de3114575792e10427c655f173b",
      "r": [
        "proton >= 0.2.4",
        "docopt #head",
        "markdown >= 0.2.0",
        "zip >= 0.2.1",
        "timezones >= 0.5.0",
        "ndb >= 0.19.4"
      ],
      "m": "0.20.0"
    },
    {
      "v": "2.0.2@fe7518eb580779dc8bc768fa06dc40fca1d45cb8",
      "r": [
        "proton >= 0.2.4",
        "docopt #head",
        "markdown >= 0.2.0",
        "zip >= 0.2.1",
        "timezones >= 0.5.0",
        "ndb >= 0.19.4"
      ],
      "m": "0.20.0"
    },
    {
      "v": "2.0.1@e938cd64292e0d0755c5fd2c9ef91a7055da1f19",
      "r": [
        "proton >= 0.2.2",
        "docopt #head",
        "markdown >= 0.2.0",
        "zip >= 0.2.1",
        "timezones >= 0.5.0"
      ],
      "m": "0.20.0"
    },
    {
      "v": "2.0.0@8c069e887a944489d434d3b4166a82f6a2e5307a",
      "r": [
        "proton >= 0.2.2",
        "docopt #head",
        "markdown >= 0.2.0",
        "zip >= 0.2.1",
        "timezones >= 0.5.0"
      ],
      "m": "0.20.0"
    },
    {
      "v": "1.8.3@4a98aed0b34406e7004a2aeed9d61f8c0a4ba6c7",
      "r": [],
      "S": "HasUnknownNimbleFile",
      "E": "missing nimble file",
      "m": "~",
      "s": "",
      "p": []
    },
    {
      "v": "1.8.2@057a1eb12599757834afd2e958fc5f3ff3872824",
      "r": [],
      "S": "HasUnknownNimbleFile",
      "E": "missing nimble file",
      "m": "~",
      "s": "",
      "p": []
    },
    {
      "v": "1.8@9d7d0a39a184580a84d674748ec6a8d7f9e8e99a",
      "r": [],
      "S": "HasUnknownNimbleFile",
      "E": "missing nimble file",
      "m": "~",
      "s": "",
      "p": []
    },
    {
      "v": "1.6@e508e5df2b224fc5abf688b0261c102427be6171",
      "r": [],
      "S": "HasUnknownNimbleFile",
      "E": "missing nimble file",
      "m": "~",
      "s": "",
      "p": []
    },
    {
      "v": "#head@683d6c9239b6abf7e85bed0b852ad6b4c635b7d2",
      "r": [
        "proton >= 0.2.4",
        "docopt >= 0.6.8",
        "markdown #v0.8.1",
        "zip >= 0.2.1",
        "timezones >= 0.5.3",
        "ndb >= 0.19.4"
      ],
      "a": "Jason R Briggs",
      "d": "Static website generation",
      "l": "Apache-2.0",
      "s": "src",
      "p": [
        "baker"
      ],
      "m": "1.0.0"
    }
  ],
  "tags": true,
  "generatedAt": "2026-05-25T11:42:23Z",
  "allDeps": {
    "packages": [
      "docopt > 1.8.3",
      "graphemes > 1.8.3",
      "markdown > 1.8.3",
      "ndb > 2.0.1",
      "proton > 1.8.3",
      "regex > 1.8.3",
      "segmentation > 1.8.3",
      "timezones > 1.8.3",
      "unicodedb > 1.8.3",
      "unicodeplus > 1.8.3",
      "zip > 1.8.3"
    ],
    "urls": [],
    "unresolved": []
  }
}