{"cv":17,"name":"dataforseo","fqn":"DataForSEO.Niminem.github.com","head":"7aa5dc45be3533e37d8082bb6c37143a52e35ce3","author":"Niminem","description":"Nim client for the DataForSEO API (v3). Zero dependencies, supports both sync and async requests.","license":"MIT","nim":"2.2.0","srcDir":"src","releases":[{"v":"0.1.0@aea08614fcb8b083d5637607a3781f5c9d035e74","r":[]},{"v":"#head@7aa5dc45be3533e37d8082bb6c37143a52e35ce3","r":[]}],"tags":false,"generatedAt":"2026-05-24T16:34:28Z","allDeps":{"packages":[],"urls":[],"unresolved":[]}}