{"cv":17,"name":"mdevolve","fqn":"MDevolve.jxy.github.com","head":"e6e1b4f5543e50e5738c5453ad01eb0ea7ca2cee","author":"Xiao-Yong Jin","description":"Integrator framework for Molecular Dynamic evolutions","license":"MIT","nim":"1.0.0","srcDir":"src","releases":[{"v":"1.0.0@2d2f4d586419049d2fdb1fbb762afc1c55d02fa1","r":[]},{"v":"0.1.1@548b703afc747eb0b256b4a018b0c20b9a93917b","r":[],"m":"0.18.1"},{"v":"#head@e6e1b4f5543e50e5738c5453ad01eb0ea7ca2cee","r":[]}],"tags":true,"generatedAt":"2026-05-25T00:37:03Z","allDeps":{"packages":[],"urls":[],"unresolved":[]}}