{
  "cv": 18,
  "name": "nimtcl",
  "fqn": "nimtcl.neroist.github.com",
  "current": "1424dd6cb13b665c28d60ad9534cd959a8415480",
  "author": "neroist",
  "description": "Low-level Tcl & Tk bindings for Nim",
  "license": "MIT",
  "nim": "2.0.0",
  "srcDir": "src",
  "releases": [
    {
      "v": "0.1.0@c272c6d70ebca495e48db4ae8b792aa20874e634",
      "r": []
    }
  ],
  "releaseCacheVersion": 18,
  "tags": true,
  "generatedAt": "2026-05-27T00:58:53Z",
  "allDeps": {
    "packages": [],
    "urls": [],
    "unresolved": []
  }
}