{
  "cv": 19,
  "name": "checksums",
  "fqn": "checksums.nim-lang.github.com",
  "current": "5c132cd332cce5d64a0da9ac3e4c9664313dccb4",
  "author": "Nim Contributors",
  "description": "Hash algorithms in Nim.",
  "license": "MIT",
  "nim": "2.0.0",
  "srcDir": "src",
  "releases": [
    {
      "v": "0.2.2@0845c735a9746188b2257ee2cff672eb6ec26e8a",
      "r": []
    },
    {
      "v": "0.2.1@f8f6bd34bfa3fe12c64b919059ad856a96efcba0",
      "r": []
    },
    {
      "v": "0.2.0@86003da1cebaf8904979579e5ebdfbaa1ce507b4",
      "r": []
    },
    {
      "v": "0.1.0@7ff0b762332d2591bbeb65df9bb86d52ea44ec01",
      "r": []
    }
  ],
  "releaseCacheVersion": 19,
  "tags": true,
  "generatedAt": "2026-05-30T12:32:54Z",
  "forge": {
    "archives": {
      "tar.gz": "/archive/refs/tags/{tag}.tar.gz",
      "zip": "/archive/refs/tags/{tag}.zip"
    },
    "releases": [
      "v0.1.0",
      "v0.2.0",
      "v0.2.1",
      "v0.2.2"
    ],
    "tagVersions": {
      "v0.1.0": "0.1.0",
      "v0.2.0": "0.2.0",
      "v0.2.1": "0.2.1",
      "v0.2.2": "0.2.2"
    },
    "latest": "v0.2.2"
  },
  "allDeps": {
    "packages": [],
    "urls": [],
    "unresolved": []
  }
}