{"cv":17,"name":"whip","fqn":"whip.mattaylor.github.com","head":"a9fd1f04ba0167727dd0dbf9235791f708147992","author":"mtaylor","description":"Fast http server based on httpbeast and nest for high performance routing","license":"MIT","skipDirs":["tests","empower"],"releases":[{"v":"0.2@a9fd1f04ba0167727dd0dbf9235791f708147992^","r":["packedjson","nest","httpbeast"]},{"v":"#head@a9fd1f04ba0167727dd0dbf9235791f708147992","r":["packedjson","nest","httpbeast"]}],"tags":true,"generatedAt":"2026-05-25T00:43:05Z","allDeps":{"packages":["asynctools","httpbeast","nest","packedjson"],"urls":[],"unresolved":["gh:iffy/asynctools","gh:timotheecour/asynctools"]}}