{"cv":17,"name":"what_the_fork","fqn":"what_the_fork.Luteva-ssh.github.com","head":"96ca51c6a5e1c2f91ae51e0c110a1da39520858d","author":"Janni Adamski","description":"What_the_fork is a terminal tool that analyses forks of a given github repo to extract changes like bugfixes, new features etc.","license":"MIT","nim":"2.2.4","srcDir":"src","binDir":"bin","bin":["what_the_fork"],"releases":[{"v":"0.1.0@420012468f142b4eeefe08829a7e1db51d51c246","r":[]},{"v":"#head@96ca51c6a5e1c2f91ae51e0c110a1da39520858d","r":[]}],"tags":false,"generatedAt":"2026-05-24T16:34:28Z","allDeps":{"packages":[],"urls":[],"unresolved":[]}}