{
  "cv": 18,
  "name": "ratel",
  "fqn": "ratel.PMunch.github.com",
  "current": "8649f0a7bf712ddc56925e41521647a1706a7186",
  "author": "Peter Munch-Ellingsen",
  "description": "Nim for microcontrollers",
  "license": "MIT",
  "nim": "1.6.4",
  "srcDir": "src",
  "installExt": [
    "nim"
  ],
  "bin": [
    "ratel"
  ],
  "releases": [
    {
      "v": "0.2.1@f993b4830284b030b78531f6e12b4ff01f79c90c",
      "r": [
        "Nimscripter",
        "cligen"
      ]
    },
    {
      "v": "0.2.0@49287db4fa1401c0d56efed6f6a88c843eca4b82",
      "r": [
        "Nimscripter",
        "cligen"
      ]
    }
  ],
  "releaseCacheVersion": 18,
  "tags": true,
  "generatedAt": "2026-05-27T01:01:19Z",
  "forge": {
    "archives": {
      "tar.gz": "/archive/refs/tags/{tag}.tar.gz",
      "zip": "/archive/refs/tags/{tag}.zip"
    },
    "releases": [
      "v0.2.0",
      "v0.2.1"
    ],
    "tagVersions": {
      "v0.2.0": "0.2.0",
      "v0.2.1": "0.2.1"
    },
    "latest": "v0.2.1"
  },
  "allDeps": {
    "packages": [
      "Nimscripter",
      "cligen"
    ],
    "urls": [],
    "unresolved": [
      "gh:disruptek/assume"
    ]
  }
}