{
  "cv": 19,
  "name": "globby",
  "fqn": "globby.treeform.github.com",
  "current": "ede865380aab166a2f7b136cabc1d9ead1857a03",
  "author": "Andre von Houck",
  "description": "Globby - Glob pattern matching for Nim.",
  "license": "MIT",
  "nim": "1.4.6",
  "srcDir": "src",
  "releases": [
    {
      "v": "0.1.0@f4bd5e1873251c73683c438bb0092809bc6798ec",
      "r": []
    }
  ],
  "releaseCacheVersion": 19,
  "tags": true,
  "generatedAt": "2026-05-28T19:03:22Z",
  "forge": {
    "archives": {
      "tar.gz": "/archive/refs/tags/{tag}.tar.gz",
      "zip": "/archive/refs/tags/{tag}.zip"
    },
    "releases": [
      "0.1.0"
    ],
    "latest": "0.1.0"
  },
  "allDeps": {
    "packages": [],
    "urls": [],
    "unresolved": []
  }
}