{"cv":17,"name":"strenc","fqn":"strenc.nim-meta.github.com","head":"1dc1b6a9c05716dc66792b99a877a9d530d159fb","author":"Danil Yarantsev (Yardanico), lit (litlighilit)","description":"A library to automatically encrypt all string constants in your programs","license":"MIT","nim":"1.0.0","srcDir":"src","releases":[{"v":"0.1.1@1dc1b6a9c05716dc66792b99a877a9d530d159fb^","r":[]},{"v":"0.1@4e72f44bb730104b3b44502cda356d14a12ae29c","r":[],"a":"Danil Yarantsev (Yardanico)"},{"v":"#head@1dc1b6a9c05716dc66792b99a877a9d530d159fb","r":[]}],"tags":true,"generatedAt":"2026-05-25T00:41:37Z","allDeps":{"packages":[],"urls":[],"unresolved":[]}}