{
  "cv": 17,
  "name": "blg",
  "fqn": "blg.capocasa.github.com",
  "head": "e239495b661b1a4a8ffeade6e3a498829db32e67",
  "author": "Carlo Capocasa",
  "description": "Static blog generator using markdown and symlinks",
  "license": "MIT",
  "nim": "2.0.0",
  "srcDir": "src",
  "bin": [
    "blg"
  ],
  "releases": [
    {
      "v": "0.2.0@e239495b661b1a4a8ffeade6e3a498829db32e67^",
      "r": [
        "margrave >= 0.3.0"
      ],
      "m": "~",
      "s": "",
      "p": []
    },
    {
      "v": "0.1.0@31ccc4d0556904d70f5074e0520c4535803e4193",
      "r": [
        "margrave >= 0.3.0"
      ],
      "m": "~",
      "s": "",
      "p": []
    },
    {
      "v": "#head@e239495b661b1a4a8ffeade6e3a498829db32e67",
      "r": [
        "margrave >= 0.3.0"
      ],
      "m": "~",
      "s": "",
      "p": []
    }
  ],
  "tags": true,
  "generatedAt": "2026-05-26T00:45:38Z",
  "allDeps": {
    "packages": [
      "margrave"
    ],
    "urls": [],
    "unresolved": []
  }
}