{
  "cv": 18,
  "name": "nimipdf",
  "fqn": "nimipdf.neroist.github.com",
  "author": "Jasmine",
  "description": "PDF backend for nimib",
  "license": "MIT",
  "nim": "1.4.0",
  "srcDir": "src",
  "releases": [
    {
      "v": "0.1.0@67f080772480027b6c1ad1b452ef06fe1a4e0d10",
      "r": [
        "nimwkhtmltox >= 0.1.0",
        "nimib"
      ]
    },
    {
      "v": "0.2.0@a4814d8cfb0031f0be2e7c3ade18c57138bc9fb8",
      "r": [
        "nimwkhtmltox >= 0.1.0",
        "nimib"
      ]
    }
  ],
  "tags": true,
  "generatedAt": "2026-05-26T13:16:57Z",
  "allDeps": {
    "packages": [
      "faststreams",
      "fusion",
      "jsony",
      "markdown",
      "mustache",
      "nimib",
      "nimwkhtmltox",
      "parsetoml",
      "results",
      "serialization",
      "stew",
      "tempfile",
      "toml_serialization",
      "unittest2"
    ],
    "urls": [],
    "unresolved": []
  }
}