{"cv":16,"name":"newfix","fqn":"newfix.inv2004.github.com","head":"03bbdb1d1cf0037a366f23167d3723f66181f888","author":"inv2004","description":"FIX Protocol parser","license":"Apache-2.0","nim":"1.4.4","srcDir":"src","installExt":["nim"],"bin":["genfix"],"releases":[{"v":"0.1.0@c68d8d31fbf7c41780d33b1dd1a404184ed60e24","r":[],"k":[],"p":[]},{"v":"0.2.1@d999b4d361fb3519f659f4904be30b77edfc7e0b","r":[]},{"v":"#head@03bbdb1d1cf0037a366f23167d3723f66181f888","r":[]}],"generatedAt":"2026-05-23T21:32:26Z","allDeps":{"packages":[],"urls":[],"unresolved":[]}}