{
  "cv": 18,
  "name": "jwt",
  "fqn": "nim-jwt.yglukhov.github.com",
  "current": "710fd315b0199f6abb17c97fb58f64987ec2be11",
  "author": "Endre Karlson",
  "description": "JSON Web Tokens for Nim",
  "license": "MIT",
  "nim": "0.19.0",
  "srcDir": "src",
  "releases": [
    {
      "v": "0.0.1@0611567742958db33429b12827646e354d8096cc",
      "r": []
    },
    {
      "v": "0.2@22e6c3126535cdfef5313b8b640140ca57ecd663",
      "r": [
        "gh:yglukhov/linktools",
        "bearssl",
        "gh:yglukhov/bearssl_pkey_decoder"
      ],
      "a": "Yuriy Glukhov"
    },
    {
      "v": "0.3@4c7c370574519b8ec812ca2013ca46e0dcbbd887",
      "r": [
        "bearssl >= 0.2.8",
        "gh:yglukhov/bearssl_pkey_decoder"
      ],
      "a": "Yuriy Glukhov",
      "m": "2.0"
    }
  ],
  "releaseCacheVersion": 18,
  "tags": true,
  "generatedAt": "2026-05-27T00:54:30Z",
  "allDeps": {
    "packages": [
      "bearssl > 0.0.1",
      "unittest2 > 0.0.1"
    ],
    "urls": [],
    "unresolved": [
      "gh:yglukhov/bearssl_pkey_decoder",
      "gh:yglukhov/linktools"
    ]
  }
}