{
  "cv": 17,
  "name": "nimagehide",
  "fqn": "nimagehide.MnlPhlp.github.com",
  "head": "1beb5968302420be67719875e138b41ec8330458",
  "author": "MnlPhlp",
  "description": "A library to hide data in images. Usable as library or cli tool.",
  "license": "MIT",
  "nim": "1.0.0",
  "srcDir": "src",
  "installExt": [
    "nim"
  ],
  "bin": [
    "nimagehide"
  ],
  "backend": "cpp",
  "releases": [
    {
      "v": "0.1.0@ece6899dc05556b353bda2dc64680580ece67392",
      "r": [
        "stb_image >= 2.3"
      ],
      "m": "~",
      "s": "",
      "k": [],
      "p": [],
      "e": ""
    },
    {
      "v": "0.1.5@77277379903d9607cda83ca7eb5f34c785bf671c",
      "r": [
        "stb_image >= 2.3",
        "cligen >= 0.9.40"
      ],
      "e": "c",
      "m": "~",
      "s": "",
      "k": [],
      "p": []
    },
    {
      "v": "0.2.0@53c742bdcf5c96ac7271639dc306d5f542842231",
      "r": [
        "stb_image >= 2.3",
        "cligen >= 0.9.40"
      ],
      "e": "c",
      "m": "~",
      "s": "",
      "k": [],
      "p": []
    },
    {
      "v": "0.2.5@ade9154a4042b62cf7ed87812de89024b04b24eb",
      "r": [
        "stb_image >= 2.3",
        "cligen >= 0.9.40"
      ],
      "e": "c",
      "m": "~",
      "s": "",
      "k": [],
      "p": []
    },
    {
      "v": "#head@1beb5968302420be67719875e138b41ec8330458",
      "r": [
        "stb_image >= 2.3",
        "cligen >= 0.9.40",
        "cli_menu >= 0.2.5"
      ],
      "e": "c",
      "m": "~",
      "s": "",
      "k": [],
      "p": []
    }
  ],
  "tags": true,
  "generatedAt": "2026-05-26T00:51:28Z",
  "allDeps": {
    "packages": [
      "cli_menu",
      "cligen > 0.1.0",
      "stb_image"
    ],
    "urls": [],
    "unresolved": []
  }
}