{
  "cv": 19,
  "name": "miniz",
  "fqn": "miniz.treeform.github.com",
  "current": "78852d53fb408432383c2e9bb625224f156c7b96",
  "author": "treeform",
  "description": "Wrapper for Miniz lib.",
  "license": "MIT",
  "nim": "1.0",
  "srcDir": "src",
  "releases": [
    {
      "v": "0.2.0@e99dc20c36a86576d983dfa14cf1db2439193861",
      "r": []
    },
    {
      "v": "0.1.0@c424ca808e2eb91382921b4a070862cd9e16d822",
      "r": [],
      "m": "0.18.1"
    }
  ],
  "releaseCacheVersion": 19,
  "tags": true,
  "generatedAt": "2026-05-28T13:28:29Z",
  "forge": {
    "archives": {
      "tar.gz": "/archive/refs/tags/{tag}.tar.gz",
      "zip": "/archive/refs/tags/{tag}.zip"
    },
    "releases": [
      "0.1.0",
      "0.2.0",
      "v0.1.0"
    ],
    "tagVersions": {
      "v0.1.0": "0.1.0"
    },
    "latest": "0.2.0"
  },
  "allDeps": {
    "packages": [],
    "urls": [],
    "unresolved": []
  }
}