{
  "cv": 19,
  "name": "animatecss",
  "fqn": "animatecss.thisago.github.com",
  "current": "7d03f0d2465d48f99a8270a53dc027197e68e85e",
  "author": "Thiago Ferreira",
  "description": "Easily use Animate.css classes",
  "license": "MIT",
  "nim": "1.0.0",
  "srcDir": "src",
  "releases": [
    {
      "v": "0.1.0@37a55398c51ab5dd03c5625f2d3d90670f642073",
      "r": []
    },
    {
      "v": "0.1.1@7d03f0d2465d48f99a8270a53dc027197e68e85e^",
      "r": []
    }
  ],
  "releaseCacheVersion": 19,
  "tags": true,
  "generatedAt": "2026-05-27T11:54:58Z",
  "allDeps": {
    "packages": [],
    "urls": [],
    "unresolved": []
  }
}