{
  "cv": 17,
  "name": "fltk",
  "fqn": "nfltk.Skrylar.github.com",
  "head": "d1b497d74a3be64a11e8b819a482022c611bcfe0",
  "author": "Skrylar",
  "description": "Fast Light Toolkit.",
  "license": "LGPL",
  "nim": "0.18.0",
  "srcDir": "src",
  "releases": [
    {
      "v": "1.3.4@f4565568d58a28d38d32cdb3303ecb03aa86ca0c",
      "r": [],
      "m": "~",
      "s": ""
    },
    {
      "v": "#head@d1b497d74a3be64a11e8b819a482022c611bcfe0",
      "r": [],
      "m": "~",
      "s": ""
    }
  ],
  "tags": true,
  "generatedAt": "2026-05-26T00:47:51Z",
  "allDeps": {
    "packages": [],
    "urls": [],
    "unresolved": []
  }
}