{
  "cv": 19,
  "name": "oauth",
  "fqn": "oauth.CORDEA.github.com",
  "current": "ec2e058fc46f04deaf3cb55eca32b3b83c614953",
  "author": "Yoshihiro Tanaka",
  "description": "OAuth library for nim",
  "license": "Apache License 2.0",
  "nim": "0.19.0",
  "srcDir": "src",
  "releases": [
    {
      "v": "0.11@ec2e058fc46f04deaf3cb55eca32b3b83c614953^",
      "r": [
        "sha1"
      ]
    },
    {
      "v": "0.10@2609e710ab76e61a503560b73618fc24eb97e8f9",
      "r": [
        "sha1"
      ]
    },
    {
      "v": "0.9@2bd6dce587881660ee033a6c0acf2bc5fe6869c8",
      "r": [
        "sha1"
      ]
    },
    {
      "v": "0.8@c458ea007bfeded5ee5e37218884db27345e739f",
      "r": [
        "sha1"
      ]
    },
    {
      "v": "0.7@b512e31d74c97932532af8e8d4735191e8c43564",
      "r": []
    },
    {
      "v": "0.6@43561b16cd3e2af666665d3fc8b137f025fc6ab4",
      "r": []
    },
    {
      "v": "0.5@79997b761012fcbad52bd5bcfeac11d6be068965",
      "r": []
    },
    {
      "v": "0.4.1@baac486ca2be79f76d6ffc66f2ef3c8550b3f77b",
      "r": []
    },
    {
      "v": "0.4@35e45f41fa2d63fdc3e5c17abcd85d199bc29e70",
      "r": []
    },
    {
      "v": "0.3@d976556fa798ef13b714b8de42ef58189e490ef4",
      "r": []
    },
    {
      "v": "0.2@df6074c0e47c08c3bc24eb0bff3c47060155c419",
      "r": []
    }
  ],
  "releaseCacheVersion": 19,
  "tags": true,
  "generatedAt": "2026-05-28T19:06:35Z",
  "forge": {
    "archives": {
      "tar.gz": "/archive/refs/tags/{tag}.tar.gz",
      "zip": "/archive/refs/tags/{tag}.zip"
    },
    "releases": [
      "v0.10",
      "v0.11",
      "v0.2",
      "v0.3",
      "v0.4",
      "v0.4.1",
      "v0.5",
      "v0.6",
      "v0.7",
      "v0.8",
      "v0.9"
    ],
    "tagVersions": {
      "v0.10": "0.10",
      "v0.11": "0.11",
      "v0.2": "0.2",
      "v0.3": "0.3",
      "v0.4": "0.4",
      "v0.4.1": "0.4.1",
      "v0.5": "0.5",
      "v0.6": "0.6",
      "v0.7": "0.7",
      "v0.8": "0.8",
      "v0.9": "0.9"
    },
    "latest": "v0.11"
  },
  "allDeps": {
    "packages": [
      "sha1 > 0.7"
    ],
    "urls": [],
    "unresolved": []
  }
}