{
  "cv": 19,
  "name": "wyhash",
  "fqn": "wyhash.nim.jackhftang.github.com",
  "current": "d087ea8a83e5ec62f1388df0945f123eb8081bdb",
  "author": "Jack Tang",
  "description": "A new awesome nimble package",
  "license": "MIT",
  "nim": "1.0.0",
  "srcDir": "src",
  "releases": [
    {
      "v": "0.1.0@ff4719f156900a5785fda32b729b6fa87522f911",
      "r": []
    }
  ],
  "releaseCacheVersion": 19,
  "tags": true,
  "generatedAt": "2026-05-27T13:34:18Z",
  "forge": {
    "archives": {
      "tar.gz": "/archive/refs/tags/{tag}.tar.gz",
      "zip": "/archive/refs/tags/{tag}.zip"
    },
    "releases": [
      "0.1.0"
    ],
    "latest": "0.1.0"
  },
  "allDeps": {
    "packages": [],
    "urls": [],
    "unresolved": []
  }
}