{
  "cv": 17,
  "name": "dnsdisc",
  "fqn": "nim-dnsdisc.status-im.github.com",
  "head": "6cb1b7e3922645275043c68e476cac1501a45e55",
  "author": "Status Research & Development GmbH",
  "description": "Nim discovery library supporting EIP-1459",
  "license": "MIT or Apache License 2.0",
  "nim": "1.2.0",
  "releases": [
    {
      "v": "0.1.0@d59adefadebe7af408f54461c29a04098702c6e2",
      "r": [
        "bearssl",
        "chronicles",
        "chronos",
        "eth",
        "secp256k1",
        "stew",
        "testutils",
        "unittest2",
        "nimcrypto"
      ],
      "m": "~"
    },
    {
      "v": "0.1.1@6cb1b7e3922645275043c68e476cac1501a45e55^",
      "r": [
        "bearssl",
        "chronicles",
        "chronos",
        "eth",
        "secp256k1",
        "stew",
        "testutils",
        "unittest2",
        "nimcrypto",
        "results"
      ],
      "m": "2.0.10"
    },
    {
      "v": "#head@6cb1b7e3922645275043c68e476cac1501a45e55",
      "r": [
        "bearssl",
        "chronicles",
        "chronos",
        "eth",
        "secp256k1",
        "stew",
        "testutils",
        "unittest2",
        "nimcrypto",
        "results"
      ],
      "m": "2.0.10"
    }
  ],
  "tags": true,
  "generatedAt": "2026-05-26T00:47:01Z",
  "allDeps": {
    "packages": [
      "bearssl",
      "chronicles",
      "chronos",
      "confutils",
      "eth",
      "faststreams",
      "httputils",
      "intops",
      "json_serialization",
      "metrics",
      "minilru",
      "nat_traversal",
      "nimcrypto",
      "results",
      "secp256k1",
      "serialization",
      "snappy",
      "sqlite3_abi",
      "stew",
      "stint",
      "testutils",
      "unittest2"
    ],
    "urls": [],
    "unresolved": []
  }
}